eWasteM/__init__.py
eWasteM/eWasteManagement.py
eWasteM-0.0.1.dist-info/LICENSE
eWasteM-0.0.1.dist-info/METADATA
eWasteM-0.0.1.dist-info/WHEEL
eWasteM-0.0.1.dist-info/top_level.txt
eWasteM-0.0.1.dist-info/RECORD
